arbm_core/__init__.py
arbm_core/core/__init__.py
arbm_core/core/mongo.py
arbm_core/core/parsing.py
arbm_core/core/publishing.py
arbm_core/core/reports.py
arbm_core/core/signals.py
arbm_core/core/utils.py
arbm_core/merging/__init__.py
arbm_core/merging/merge.py
arbm_core/merging/merge_projects.py
arbm_core/private/__init__.py
arbm_core/private/investors.py
arbm_core/private/linkedin.py
arbm_core/private/logging.py
arbm_core/private/projects.py
arbm_core/private/queue.py
arbm_core/private/relationships.py
arbm_core/private/signals.py
arbm_core/private/twitter.py
arbm_core/private/users.py
arbm_core/public/__init__.py
arbm_core/public/logging.py
arbm_core/public/projects.py
arbm_core/public/promo.py
arbm_core/public/schemas/__init__.py
arbm_core/public/schemas/feed.py
arbm_core/public/schemas/graph.py
arbm_core/public/schemas/project.py
arbm_core/public/schemas/signals.py
arbm_core/public/schemas/user.py
arbm_core/public/users.py
arbm_core/tests/test_signals.py
arbm_core/vc_graph/__init__.py
arbm_core/vc_graph/collections.py
arbm_core/vc_graph/mongo_migrate.py
arbm_core/vc_graph/schemas/__init__.py
arbm_core/vc_graph/schemas/entities.py
arbm_core/vc_graph/schemas/signals.py
arbm_core-0.1.0.dist-info/METADATA
arbm_core-0.1.0.dist-info/WHEEL
arbm_core-0.1.0.dist-info/RECORD
